task3/Intergrated Template/ALU.sv
module ALU (
    input  logic [31:0] op1,
    input  logic [31:0] op2,
    input  logic [2:0]  control,
    output logic [31:0] result,
    output logic        zero
);
    always_comb begin
        case (control)
            3'b000: result = op1 + op2;    // ADD
            3'b001: result = op1 - op2;    // SUB

            default: result = 32'b0;
        endcase
        zero = (result == 32'b0); // flag for set_0
    end
endmodule

task3/Intergrated Template/RegisterFile.sv
module RegisterFile (
    input  logic          clk,
    input  logic          reg_write,
    input  logic [4:0]    read_addr1, read_addr2, write_addr,
    input  logic [31:0]   write_data,
    output logic [31:0]   read_data1, read_data2
);
    logic [31:0] registers [0:31]; // 32*32 registers

    // Asynchronous read
    assign read_data1 = registers[read_addr1];
    assign read_data2 = registers[read_addr2];

    // Synchronous write
    always_ff @(posedge clk) begin
        if (reg_write) begin
            registers[write_addr] <= write_data;
        end
    end
endmodule

task3/Intergrated Template/RGALU.sv
module RGALU(
    input logic clk,
    input logic reg_write,
    input logic [4:0] read_addr1,
    input logic [4:0] read_addr2,
    input logic [4:0] write_addr,
    input logic [31:0] write_data,
    input logic [2:0] alu_control,
    input logic alu_src,
    input logic [31:0] imm32,
    output logic [31:0] alu_result,
    output logic zero_flag,
    output logic [31:0] reg_a0 
);
    logic [31:0] read_data1, read_data2;
    logic [31:0] op2;

    // Multiplexer for op2
    assign op2 = alu_src ? imm32 : read_data2;

    // Inst. Register File
    RegisterFile reg_file (
        .clk(clk),
        .reg_write(reg_write),
        .read_addr1(read_addr1),
        .read_addr2(read_addr2),
        .write_addr(write_addr),
        .write_data(write_data),
        .read_data1(read_data1),
        .read_data2(read_data2)
    );

    // Inst. ALU
    ALU alu (
        .op1(read_data1), // Always use read_data1
        .op2(op2),        // select op2
        .control(alu_control),
        .result(alu_result),
        .zero(zero_flag)
    );

    // Output register a0 (reg[10])
    assign reg_a0 = reg_file.registers[10];
endmodule

task3/SignExtender.sv
module SignExtender (
    input  logic [31:0] instruction,
    output logic [31:0] imm32
);
    logic signed [31:0] signedImm32;

    always_comb begin
        case (instruction[6:0])
            7'b1100011: begin  // BNE

                signedImm32 = $signed({instruction[31], instruction[7], instruction[30:25], instruction[11:8], 1'b0});
                imm32 = signedImm32;
            end

            7'b0010011: begin  // ADDI

                signedImm32 = $signed(instruction[31:20]);  // 符号扩展
                imm32 = signedImm32;
            end

            default: begin
                // default output = 0
                imm32 = 32'b0;
            end
        endcase
    end
endmodule

task3/Intergrated Template/ControlUnit.sv
module ControlUnit (
    input  logic [6:0] opcode,
    input  logic       zero_flag, // ALU zero flag input
    output logic       reg_write,
    output logic       alu_src,
    output logic       pc_src,
    output logic [2:0] alu_control
);
    always_comb begin
        // Default values
        reg_write = 0;
        alu_src = 0;
        pc_src = 0;
        alu_control = 3'b000;

        case (opcode)
            7'b0010011: begin // ADDI
                reg_write = 1;
                alu_src = 1;
                alu_control = 3'b000; // ALU ADD
            end
            7'b1100011: begin // BNE
                pc_src = ~zero_flag; // Jump if not equal
                alu_control = 3'b001; // ALU SUB
            end
            default: begin
                // 测试用，error handling
            end
        endcase
    end
endmodule

task3/Intergrated Template/InstructionMemory.sv
module InstructionMemory(
    input logic [31:0] pc,
    output logic [31:0] instruction
);
    logic [31:0] program_memory [0:255];

    // Initialize memory
    initial begin
        $readmemh("program.hex", program_memory); // Load instructions from program.hex
    end

    assign instruction = program_memory[pc[9:2]]; // Use PC[9:2] as index
endmodule

task3/Intergrated Template/PCModule.sv
module PCModule(
    input logic clk,
    input logic rst,
    input logic[31:0] branch_target,
    input logic pc_src,
    output logic[31:0] pc
);
    logic[31:0] next_pc;

    always_ff @(posedge clk or posedge rst) begin
        if (rst)
            pc <= 32'b0; // Reset PC to 0
        else
            pc <= next_pc; // Update PC
    end

    logic[31:0] inc_pc = pc + 32'd4; // PC += 4

    assign next_pc = pc_src ? branch_target : inc_pc; // go to PC_next based on pc_src
endmodule

task3/Intergrated Template/TopCPU.sv
module TopCPU(
    input logic clk,
    input logic rst,
    output logic [31:0] a0
);
    // Internal signals
    logic [31:0] pc, branch_target, instruction;
    logic [31:0] imm32, write_data, alu_result;
    logic reg_write, alu_src, pc_src, zero_flag;
    logic [2:0] alu_control;

    // PC Module
    PCModule pc_module (
        .clk(clk),
        .rst(rst),
        .branch_target(branch_target),
        .pc_src(pc_src),
        .pc(pc)
    );

    // Instruction Memory
    InstructionMemory instruction_memory (
        .pc(pc),
        .instruction(instruction)
    );

    // Control Unit
    ControlUnit control_unit (
        .opcode(instruction[6:0]),
        .zero_flag(zero_flag),     // Connect zero_flag
        .reg_write(reg_write),
        .alu_src(alu_src),         // alu_src signal
        .pc_src(pc_src),
        .alu_control(alu_control)
    );

    // SignExtender
    SignExtender sign_extender (
        .instruction(instruction), // From full instruction to get imm
        .imm32(imm32)              // Extended immediate output
    );

    // RGALU
    RGALU reg_alu (
        .clk(clk),
        .reg_write(reg_write),
        .read_addr1(instruction[19:15]),  // rs1
        .read_addr2(instruction[24:20]),  // rs2
        .write_addr(instruction[11:7]),   // rd
        .write_data(write_data),          // Data to write back
        .alu_control(alu_control),
        .alu_src(alu_src),                // Pass alu_src to RGALU
        .imm32(imm32),                    // Pass imm32 to RGALU
        .alu_result(alu_result),
        .zero_flag(zero_flag),
        .reg_a0(a0)                       // Output register a0 (x10)
    );

    // Write data for register file
    assign write_data = alu_result;

    // Branch target calculation
    assign branch_target = pc + (imm32);

endmodule

task3/Intergrated Template/TopCPU.vcd
$version Generated by VerilatedVcd $end
$date Tue Nov 19 20:07:29 2024 $end
$timescale 1ps $end

 $scope module TOP $end
  $var wire 32 T a0 [31:0] $end
  $var wire  1 R clk $end
  $var wire  1 S rst $end
  $scope module TopCPU $end
   $var wire 32 T a0 [31:0] $end
   $var wire  3 J alu_control [2:0] $end
   $var wire 32 E alu_result [31:0] $end
   $var wire  1 G alu_src $end
   $var wire 32 V branch_target [31:0] $end
   $var wire  1 R clk $end
   $var wire 32 D imm32 [31:0] $end
   $var wire 32 C instruction [31:0] $end
   $var wire 32 U pc [31:0] $end
   $var wire  1 H pc_src $end
   $var wire  1 F reg_write $end
   $var wire  1 S rst $end
   $var wire 32 E write_data [31:0] $end
   $var wire  1 I zero_flag $end
   $scope module control_unit $end
    $var wire  3 J alu_control [2:0] $end
    $var wire  1 G alu_src $end
    $var wire  7 K opcode [6:0] $end
    $var wire  1 H pc_src $end
    $var wire  1 F reg_write $end
    $var wire  1 I zero_flag $end
   $upscope $end
   $scope module instruction_memory $end
    $var wire 32 C instruction [31:0] $end
    $var wire 32 U pc [31:0] $end
   $upscope $end
   $scope module pc_module $end
    $var wire 32 V branch_target [31:0] $end
    $var wire  1 R clk $end
    $var wire 32 X inc_pc [31:0] $end
    $var wire 32 W next_pc [31:0] $end
    $var wire 32 U pc [31:0] $end
    $var wire  1 H pc_src $end
    $var wire  1 S rst $end
   $upscope $end
   $scope module reg_alu $end
    $var wire  3 J alu_control [2:0] $end
    $var wire 32 E alu_result [31:0] $end
    $var wire  1 G alu_src $end
    $var wire  1 R clk $end
    $var wire 32 D imm32 [31:0] $end
    $var wire 32 P op2 [31:0] $end
    $var wire  5 L read_addr1 [4:0] $end
    $var wire  5 M read_addr2 [4:0] $end
    $var wire 32 O read_data1 [31:0] $end
    $var wire 32 Y read_data2 [31:0] $end
    $var wire 32 T reg_a0 [31:0] $end
    $var wire  1 F reg_write $end
    $var wire  5 N write_addr [4:0] $end
    $var wire 32 E write_data [31:0] $end
    $var wire  1 I zero_flag $end
    $scope module alu $end
     $var wire  3 J control [2:0] $end
     $var wire 32 O op1 [31:0] $end
     $var wire 32 P op2 [31:0] $end
     $var wire 32 E result [31:0] $end
     $var wire  1 I zero $end
    $upscope $end
    $scope module reg_file $end
     $var wire  1 R clk $end
     $var wire  5 L read_addr1 [4:0] $end
     $var wire  5 M read_addr2 [4:0] $end
     $var wire 32 O read_data1 [31:0] $end
     $var wire 32 Y read_data2 [31:0] $end
     $var wire  1 F reg_write $end
     $var wire 32 # registers[0] [31:0] $end
     $var wire 32 - registers[10] [31:0] $end
     $var wire 32 . registers[11] [31:0] $end
     $var wire 32 / registers[12] [31:0] $end
     $var wire 32 0 registers[13] [31:0] $end
     $var wire 32 1 registers[14] [31:0] $end
     $var wire 32 2 registers[15] [31:0] $end
     $var wire 32 3 registers[16] [31:0] $end
     $var wire 32 4 registers[17] [31:0] $end
     $var wire 32 5 registers[18] [31:0] $end
     $var wire 32 6 registers[19] [31:0] $end
     $var wire 32 $ registers[1] [31:0] $end
     $var wire 32 7 registers[20] [31:0] $end
     $var wire 32 8 registers[21] [31:0] $end
     $var wire 32 9 registers[22] [31:0] $end
     $var wire 32 : registers[23] [31:0] $end
     $var wire 32 ; registers[24] [31:0] $end
     $var wire 32 < registers[25] [31:0] $end
     $var wire 32 = registers[26] [31:0] $end
     $var wire 32 > registers[27] [31:0] $end
     $var wire 32 ? registers[28] [31:0] $end
     $var wire 32 @ registers[29] [31:0] $end
     $var wire 32 % registers[2] [31:0] $end
     $var wire 32 A registers[30] [31:0] $end
     $var wire 32 B registers[31] [31:0] $end
     $var wire 32 & registers[3] [31:0] $end
     $var wire 32 ' registers[4] [31:0] $end
     $var wire 32 ( registers[5] [31:0] $end
     $var wire 32 ) registers[6] [31:0] $end
     $var wire 32 * registers[7] [31:0] $end
     $var wire 32 + registers[8] [31:0] $end
     $var wire 32 , registers[9] [31:0] $end
     $var wire  5 N write_addr [4:0] $end
     $var wire 32 E write_data [31:0] $end
    $upscope $end
   $upscope $end
   $scope module sign_extender $end
    $var wire 32 D imm32 [31:0] $end
    $var wire 32 C instruction [31:0] $end
    $var wire 32 Q signedImm32 [31:0] $end
   $upscope $end
  $upscope $end
 $upscope $end
$enddefinitions $end


#0
b00000000000000000000000000000000 #
b00000000000000000000000000000000 $
b00000000000000000000000000000000 %
b00000000000000000000000000000000 &
b00000000000000000000000000000000 '
b00000000000000000000000000000000 (
b00000000000000000000000000000000 )
b00000000000000000000000000000000 *
b00000000000000000000000000000000 +
b00000000000000000000000000000000 ,
b00000000000000000000000000000000 -
b00000000000000000000000000000000 .
b00000000000000000000000000000000 /
b00000000000000000000000000000000 0
b00000000000000000000000000000000 1
b00000000000000000000000000000000 2
b00000000000000000000000000000000 3
b00000000000000000000000000000000 4
b00000000000000000000000000000000 5
b00000000000000000000000000000000 6
b00000000000000000000000000000000 7
b00000000000000000000000000000000 8
b00000000000000000000000000000000 9
b00000000000000000000000000000000 :
b00000000000000000000000000000000 ;
b00000000000000000000000000000000 <
b00000000000000000000000000000000 =
b00000000000000000000000000000000 >
b00000000000000000000000000000000 ?
b00000000000000000000000000000000 @
b00000000000000000000000000000000 A
b00000000000000000000000000000000 B
b00001111111100000000001100010011 C
b00000000000000000000000011111111 D
b00000000000000000000000011111111 E
1F
1G
0H
0I
b000 J
b0010011 K
b00000 L
b11111 M
b00110 N
b00000000000000000000000000000000 O
b00000000000000000000000011111111 P
b00000000000000000000000011111111 Q
1R
1S
b00000000000000000000000000000000 T
b00000000000000000000000000000000 U
b00000000000000000000000011111111 V
b00000000000000000000000000000100 W
b00000000000000000000000000000100 X
b00000000000000000000000000000000 Y
#2
0R
#4
b00000000000000000000000011111111 )
1R
#6
0R
0S
#8
b00000000000000000000010100010011 C
b00000000000000000000000000000000 D
b00000000000000000000000000000000 E
1I
b00000 M
b01010 N
b00000000000000000000000000000000 P
b00000000000000000000000000000000 Q
1R
b00000000000000000000000000000100 U
b00000000000000000000000000000100 V
b00000000000000000000000000001000 W
b00000000000000000000000000001000 X
#10
0R
#12
b00000000000000000000010110010011 C
b01011 N
1R
b00000000000000000000000000001000 U
b00000000000000000000000000001000 V
b00000000000000000000000000001100 W
b00000000000000000000000000001100 X
#14
0R
#16
b00000000000001011000010100010011 C
b01011 L
b01010 N
1R
b00000000000000000000000000001100 U
b00000000000000000000000000001100 V
b00000000000000000000000000010000 W
b00000000000000000000000000010000 X
#18
0R
#20
b00000000000101011000010110010011 C
b00000000000000000000000000000001 D
b00000000000000000000000000000001 E
0I
b00001 M
b01011 N
b00000000000000000000000000000001 P
b00000000000000000000000000000001 Q
1R
b00000000000000000000000000010000 U
b00000000000000000000000000010001 V
b00000000000000000000000000010100 W
b00000000000000000000000000010100 X
#22
0R
#24
b00000000000000000000000000000001 .
b11111110011001011001110011100011 C
b11111111111111111111111111111000 D
b11111111111111111111111100000010 E
0F
0G
1H
b001 J
b1100011 K
b00110 M
b11001 N
b00000000000000000000000000000001 O
b00000000000000000000000011111111 P
b11111111111111111111111111111000 Q
1R
b00000000000000000000000000010100 U
b00000000000000000000000000001100 V
b00000000000000000000000000001100 W
b00000000000000000000000000011000 X
b00000000000000000000000011111111 Y
#26
0R
#28
b00000000000001011000010100010011 C
b00000000000000000000000000000000 D
b00000000000000000000000000000001 E
1F
1G
0H
b000 J
b0010011 K
b00000 M
b01010 N
b00000000000000000000000000000000 P
b00000000000000000000000000000000 Q
1R
b00000000000000000000000000001100 U
b00000000000000000000000000010000 W
b00000000000000000000000000010000 X
b00000000000000000000000000000000 Y
#30
0R
#32
b00000000000000000000000000000001 -
b00000000000101011000010110010011 C
b00000000000000000000000000000001 D
b00000000000000000000000000000010 E
b00001 M
b01011 N
b00000000000000000000000000000001 P
b00000000000000000000000000000001 Q
1R
b00000000000000000000000000000001 T
b00000000000000000000000000010000 U
b00000000000000000000000000010001 V
b00000000000000000000000000010100 W
b00000000000000000000000000010100 X
#34
0R
#36
b00000000000000000000000000000010 .
b11111110011001011001110011100011 C
b11111111111111111111111111111000 D
b11111111111111111111111100000011 E
0F
0G
1H
b001 J
b1100011 K
b00110 M
b11001 N
b00000000000000000000000000000010 O
b00000000000000000000000011111111 P
b11111111111111111111111111111000 Q
1R
b00000000000000000000000000010100 U
b00000000000000000000000000001100 V
b00000000000000000000000000001100 W
b00000000000000000000000000011000 X
b00000000000000000000000011111111 Y
#38
0R
#40
b00000000000001011000010100010011 C
b00000000000000000000000000000000 D
b00000000000000000000000000000010 E
1F
1G
0H
b000 J
b0010011 K
b00000 M
b01010 N
b00000000000000000000000000000000 P
b00000000000000000000000000000000 Q
1R
b00000000000000000000000000001100 U
b00000000000000000000000000010000 W
b00000000000000000000000000010000 X
b00000000000000000000000000000000 Y
#42
0R
#44
b00000000000000000000000000000010 -
b00000000000101011000010110010011 C
b00000000000000000000000000000001 D
b00000000000000000000000000000011 E
b00001 M
b01011 N
b00000000000000000000000000000001 P
b00000000000000000000000000000001 Q
1R
b00000000000000000000000000000010 T
b00000000000000000000000000010000 U
b00000000000000000000000000010001 V
b00000000000000000000000000010100 W
b00000000000000000000000000010100 X
#46
0R
#48
b00000000000000000000000000000011 .
b11111110011001011001110011100011 C
b11111111111111111111111111111000 D
b11111111111111111111111100000100 E
0F
0G
1H
b001 J
b1100011 K
b00110 M
b11001 N
b00000000000000000000000000000011 O
b00000000000000000000000011111111 P
b11111111111111111111111111111000 Q
1R
b00000000000000000000000000010100 U
b00000000000000000000000000001100 V
b00000000000000000000000000001100 W
b00000000000000000000000000011000 X
b00000000000000000000000011111111 Y
#50
0R
#52
b00000000000001011000010100010011 C
b00000000000000000000000000000000 D
b00000000000000000000000000000011 E
1F
1G
0H
b000 J
b0010011 K
b00000 M
b01010 N
b00000000000000000000000000000000 P
b00000000000000000000000000000000 Q
1R
b00000000000000000000000000001100 U
b00000000000000000000000000010000 W
b00000000000000000000000000010000 X
b00000000000000000000000000000000 Y
#54
0R
#56
b00000000000000000000000000000011 -
b00000000000101011000010110010011 C
b00000000000000000000000000000001 D
b00000000000000000000000000000100 E
b00001 M
b01011 N
b00000000000000000000000000000001 P
b00000000000000000000000000000001 Q
1R
b00000000000000000000000000000011 T
b00000000000000000000000000010000 U
b00000000000000000000000000010001 V
b00000000000000000000000000010100 W
b00000000000000000000000000010100 X
#58
0R
#60
b00000000000000000000000000000100 .
b11111110011001011001110011100011 C
b11111111111111111111111111111000 D
b11111111111111111111111100000101 E
0F
0G
1H
b001 J
b1100011 K
b00110 M
b11001 N
b00000000000000000000000000000100 O
b00000000000000000000000011111111 P
b11111111111111111111111111111000 Q
1R
b00000000000000000000000000010100 U
b00000000000000000000000000001100 V
b00000000000000000000000000001100 W
b00000000000000000000000000011000 X
b00000000000000000000000011111111 Y
#62
0R
#64
b00000000000001011000010100010011 C
b00000000000000000000000000000000 D
b00000000000000000000000000000100 E
1F
1G
0H
b000 J
b0010011 K
b00000 M
b01010 N
b00000000000000000000000000000000 P
b00000000000000000000000000000000 Q
1R
b00000000000000000000000000001100 U
b00000000000000000000000000010000 W
b00000000000000000000000000010000 X
b00000000000000000000000000000000 Y
#66
0R
#68
b00000000000000000000000000000100 -
b00000000000101011000010110010011 C
b00000000000000000000000000000001 D
b00000000000000000000000000000101 E
b00001 M
b01011 N
b00000000000000000000000000000001 P
b00000000000000000000000000000001 Q
1R
b00000000000000000000000000000100 T
b00000000000000000000000000010000 U
b00000000000000000000000000010001 V
b00000000000000000000000000010100 W
b00000000000000000000000000010100 X
#70
0R
#72
b00000000000000000000000000000101 .
b11111110011001011001110011100011 C
b11111111111111111111111111111000 D
b11111111111111111111111100000110 E
0F
0G
1H
b001 J
b1100011 K
b00110 M
b11001 N
b00000000000000000000000000000101 O
b00000000000000000000000011111111 P
b11111111111111111111111111111000 Q
1R
b00000000000000000000000000010100 U
b00000000000000000000000000001100 V
b00000000000000000000000000001100 W
b00000000000000000000000000011000 X
b00000000000000000000000011111111 Y
#74
0R
#76
b00000000000001011000010100010011 C
b00000000000000000000000000000000 D
b00000000000000000000000000000101 E
1F
1G
0H
b000 J
b0010011 K
b00000 M
b01010 N
b00000000000000000000000000000000 P
b00000000000000000000000000000000 Q
1R
b00000000000000000000000000001100 U
b00000000000000000000000000010000 W
b00000000000000000000000000010000 X
b00000000000000000000000000000000 Y
#78
0R
#80
b00000000000000000000000000000101 -
b00000000000101011000010110010011 C
b00000000000000000000000000000001 D
b00000000000000000000000000000110 E
b00001 M
b01011 N
b00000000000000000000000000000001 P
b00000000000000000000000000000001 Q
1R
b00000000000000000000000000000101 T
b00000000000000000000000000010000 U
b00000000000000000000000000010001 V
b00000000000000000000000000010100 W
b00000000000000000000000000010100 X
#82
0R
#84
b00000000000000000000000000000110 .
b11111110011001011001110011100011 C
b11111111111111111111111111111000 D
b11111111111111111111111100000111 E
0F
0G
1H
b001 J
b1100011 K
b00110 M
b11001 N
b00000000000000000000000000000110 O
b00000000000000000000000011111111 P
b11111111111111111111111111111000 Q
1R
b00000000000000000000000000010100 U
b00000000000000000000000000001100 V
b00000000000000000000000000001100 W
b00000000000000000000000000011000 X
b00000000000000000000000011111111 Y
#86
0R
#88
b00000000000001011000010100010011 C
b00000000000000000000000000000000 D
b00000000000000000000000000000110 E
1F
1G
0H
b000 J
b0010011 K
b00000 M
b01010 N
b00000000000000000000000000000000 P
b00000000000000000000000000000000 Q
1R
b00000000000000000000000000001100 U
b00000000000000000000000000010000 W
b00000000000000000000000000010000 X
b00000000000000000000000000000000 Y
#90
0R
#92
b00000000000000000000000000000110 -
b00000000000101011000010110010011 C
b00000000000000000000000000000001 D
b00000000000000000000000000000111 E
b00001 M
b01011 N
b00000000000000000000000000000001 P
b00000000000000000000000000000001 Q
1R
b00000000000000000000000000000110 T
b00000000000000000000000000010000 U
b00000000000000000000000000010001 V
b00000000000000000000000000010100 W
b00000000000000000000000000010100 X
#94
0R
#96
b00000000000000000000000000000111 .
b11111110011001011001110011100011 C
b11111111111111111111111111111000 D
b11111111111111111111111100001000 E
0F
0G
1H
b001 J
b1100011 K
b00110 M
b11001 N
b00000000000000000000000000000111 O
b00000000000000000000000011111111 P
b11111111111111111111111111111000 Q
1R
b00000000000000000000000000010100 U
b00000000000000000000000000001100 V
b00000000000000000000000000001100 W
b00000000000000000000000000011000 X
b00000000000000000000000011111111 Y
#98
0R
#100
b00000000000001011000010100010011 C
b00000000000000000000000000000000 D
b00000000000000000000000000000111 E
1F
1G
0H
b000 J
b0010011 K
b00000 M
b01010 N
b00000000000000000000000000000000 P
b00000000000000000000000000000000 Q
1R
b00000000000000000000000000001100 U
b00000000000000000000000000010000 W
b00000000000000000000000000010000 X
b00000000000000000000000000000000 Y
#102
0R
#104
b00000000000000000000000000000111 -
b00000000000101011000010110010011 C
b00000000000000000000000000000001 D
b00000000000000000000000000001000 E
b00001 M
b01011 N
b00000000000000000000000000000001 P
b00000000000000000000000000000001 Q
1R
b00000000000000000000000000000111 T
b00000000000000000000000000010000 U
b00000000000000000000000000010001 V
b00000000000000000000000000010100 W
b00000000000000000000000000010100 X
#106
0R
#108
b00000000000000000000000000001000 .
b11111110011001011001110011100011 C
b11111111111111111111111111111000 D
b11111111111111111111111100001001 E
0F
0G
1H
b001 J
b1100011 K
b00110 M
b11001 N
b00000000000000000000000000001000 O
b00000000000000000000000011111111 P
b11111111111111111111111111111000 Q
1R
b00000000000000000000000000010100 U
b00000000000000000000000000001100 V
b00000000000000000000000000001100 W
b00000000000000000000000000011000 X
b00000000000000000000000011111111 Y
#110
0R
#112
b00000000000001011000010100010011 C
b00000000000000000000000000000000 D
b00000000000000000000000000001000 E
1F
1G
0H
b000 J
b0010011 K
b00000 M
b01010 N
b00000000000000000000000000000000 P
b00000000000000000000000000000000 Q
1R
b00000000000000000000000000001100 U
b00000000000000000000000000010000 W
b00000000000000000000000000010000 X
b00000000000000000000000000000000 Y
#114
0R
#116
b00000000000000000000000000001000 -
b00000000000101011000010110010011 C
b00000000000000000000000000000001 D
b00000000000000000000000000001001 E
b00001 M
b01011 N
b00000000000000000000000000000001 P
b00000000000000000000000000000001 Q
1R
b00000000000000000000000000001000 T
b00000000000000000000000000010000 U
b00000000000000000000000000010001 V
b00000000000000000000000000010100 W
b00000000000000000000000000010100 X
#118
0R
#120
b00000000000000000000000000001001 .
b11111110011001011001110011100011 C
b11111111111111111111111111111000 D
b11111111111111111111111100001010 E
0F
0G
1H
b001 J
b1100011 K
b00110 M
b11001 N
b00000000000000000000000000001001 O
b00000000000000000000000011111111 P
b11111111111111111111111111111000 Q
1R
b00000000000000000000000000010100 U
b00000000000000000000000000001100 V
b00000000000000000000000000001100 W
b00000000000000000000000000011000 X
b00000000000000000000000011111111 Y
#122
0R
#124
b00000000000001011000010100010011 C
b00000000000000000000000000000000 D
b00000000000000000000000000001001 E
1F
1G
0H
b000 J
b0010011 K
b00000 M
b01010 N
b00000000000000000000000000000000 P
b00000000000000000000000000000000 Q
1R
b00000000000000000000000000001100 U
b00000000000000000000000000010000 W
b00000000000000000000000000010000 X
b00000000000000000000000000000000 Y
#126
0R
#128
b00000000000000000000000000001001 -
b00000000000101011000010110010011 C
b00000000000000000000000000000001 D
b00000000000000000000000000001010 E
b00001 M
b01011 N
b00000000000000000000000000000001 P
b00000000000000000000000000000001 Q
1R
b00000000000000000000000000001001 T
b00000000000000000000000000010000 U
b00000000000000000000000000010001 V
b00000000000000000000000000010100 W
b00000000000000000000000000010100 X
#130
0R
#132
b00000000000000000000000000001010 .
b11111110011001011001110011100011 C
b11111111111111111111111111111000 D
b11111111111111111111111100001011 E
0F
0G
1H
b001 J
b1100011 K
b00110 M
b11001 N
b00000000000000000000000000001010 O
b00000000000000000000000011111111 P
b11111111111111111111111111111000 Q
1R
b00000000000000000000000000010100 U
b00000000000000000000000000001100 V
b00000000000000000000000000001100 W
b00000000000000000000000000011000 X
b00000000000000000000000011111111 Y
#134
0R
#136
b00000000000001011000010100010011 C
b00000000000000000000000000000000 D
b00000000000000000000000000001010 E
1F
1G
0H
b000 J
b0010011 K
b00000 M
b01010 N
b00000000000000000000000000000000 P
b00000000000000000000000000000000 Q
1R
b00000000000000000000000000001100 U
b00000000000000000000000000010000 W
b00000000000000000000000000010000 X
b00000000000000000000000000000000 Y
#138
0R
#140
b00000000000000000000000000001010 -
b00000000000101011000010110010011 C
b00000000000000000000000000000001 D
b00000000000000000000000000001011 E
b00001 M
b01011 N
b00000000000000000000000000000001 P
b00000000000000000000000000000001 Q
1R
b00000000000000000000000000001010 T
b00000000000000000000000000010000 U
b00000000000000000000000000010001 V
b00000000000000000000000000010100 W
b00000000000000000000000000010100 X
#142
0R
#144
b00000000000000000000000000001011 .
b11111110011001011001110011100011 C
b11111111111111111111111111111000 D
b11111111111111111111111100001100 E
0F
0G
1H
b001 J
b1100011 K
b00110 M
b11001 N
b00000000000000000000000000001011 O
b00000000000000000000000011111111 P
b11111111111111111111111111111000 Q
1R
b00000000000000000000000000010100 U
b00000000000000000000000000001100 V
b00000000000000000000000000001100 W
b00000000000000000000000000011000 X
b00000000000000000000000011111111 Y
#146
0R
#148
b00000000000001011000010100010011 C
b00000000000000000000000000000000 D
b00000000000000000000000000001011 E
1F
1G
0H
b000 J
b0010011 K
b00000 M
b01010 N
b00000000000000000000000000000000 P
b00000000000000000000000000000000 Q
1R
b00000000000000000000000000001100 U
b00000000000000000000000000010000 W
b00000000000000000000000000010000 X
b00000000000000000000000000000000 Y
#150
0R
#152
b00000000000000000000000000001011 -
b00000000000101011000010110010011 C
b00000000000000000000000000000001 D
b00000000000000000000000000001100 E
b00001 M
b01011 N
b00000000000000000000000000000001 P
b00000000000000000000000000000001 Q
1R
b00000000000000000000000000001011 T
b00000000000000000000000000010000 U
b00000000000000000000000000010001 V
b00000000000000000000000000010100 W
b00000000000000000000000000010100 X
#154
0R
#156
b00000000000000000000000000001100 .
b11111110011001011001110011100011 C
b11111111111111111111111111111000 D
b11111111111111111111111100001101 E
0F
0G
1H
b001 J
b1100011 K
b00110 M
b11001 N
b00000000000000000000000000001100 O
b00000000000000000000000011111111 P
b11111111111111111111111111111000 Q
1R
b00000000000000000000000000010100 U
b00000000000000000000000000001100 V
b00000000000000000000000000001100 W
b00000000000000000000000000011000 X
b00000000000000000000000011111111 Y
#158
0R
#160
b00000000000001011000010100010011 C
b00000000000000000000000000000000 D
b00000000000000000000000000001100 E
1F
1G
0H
b000 J
b0010011 K
b00000 M
b01010 N
b00000000000000000000000000000000 P
b00000000000000000000000000000000 Q
1R
b00000000000000000000000000001100 U
b00000000000000000000000000010000 W
b00000000000000000000000000010000 X
b00000000000000000000000000000000 Y
#162
0R
#164
b00000000000000000000000000001100 -
b00000000000101011000010110010011 C
b00000000000000000000000000000001 D
b00000000000000000000000000001101 E
b00001 M
b01011 N
b00000000000000000000000000000001 P
b00000000000000000000000000000001 Q
1R
b00000000000000000000000000001100 T
b00000000000000000000000000010000 U
b00000000000000000000000000010001 V
b00000000000000000000000000010100 W
b00000000000000000000000000010100 X
#166
0R
#168
b00000000000000000000000000001101 .
b11111110011001011001110011100011 C
b11111111111111111111111111111000 D
b11111111111111111111111100001110 E
0F
0G
1H
b001 J
b1100011 K
b00110 M
b11001 N
b00000000000000000000000000001101 O
b00000000000000000000000011111111 P
b11111111111111111111111111111000 Q
1R
b00000000000000000000000000010100 U
b00000000000000000000000000001100 V
b00000000000000000000000000001100 W
b00000000000000000000000000011000 X
b00000000000000000000000011111111 Y
#170
0R
#172
b00000000000001011000010100010011 C
b00000000000000000000000000000000 D
b00000000000000000000000000001101 E
1F
1G
0H
b000 J
b0010011 K
b00000 M
b01010 N
b00000000000000000000000000000000 P
b00000000000000000000000000000000 Q
1R
b00000000000000000000000000001100 U
b00000000000000000000000000010000 W
b00000000000000000000000000010000 X
b00000000000000000000000000000000 Y
#174
0R
#176
b00000000000000000000000000001101 -
b00000000000101011000010110010011 C
b00000000000000000000000000000001 D
b00000000000000000000000000001110 E
b00001 M
b01011 N
b00000000000000000000000000000001 P
b00000000000000000000000000000001 Q
1R
b00000000000000000000000000001101 T
b00000000000000000000000000010000 U
b00000000000000000000000000010001 V
b00000000000000000000000000010100 W
b00000000000000000000000000010100 X
#178
0R
#180
b00000000000000000000000000001110 .
b11111110011001011001110011100011 C
b11111111111111111111111111111000 D
b11111111111111111111111100001111 E
0F
0G
1H
b001 J
b1100011 K
b00110 M
b11001 N
b00000000000000000000000000001110 O
b00000000000000000000000011111111 P
b11111111111111111111111111111000 Q
1R
b00000000000000000000000000010100 U
b00000000000000000000000000001100 V
b00000000000000000000000000001100 W
b00000000000000000000000000011000 X
b00000000000000000000000011111111 Y
#182
0R
#184
b00000000000001011000010100010011 C
b00000000000000000000000000000000 D
b00000000000000000000000000001110 E
1F
1G
0H
b000 J
b0010011 K
b00000 M
b01010 N
b00000000000000000000000000000000 P
b00000000000000000000000000000000 Q
1R
b00000000000000000000000000001100 U
b00000000000000000000000000010000 W
b00000000000000000000000000010000 X
b00000000000000000000000000000000 Y
#186
0R
#188
b00000000000000000000000000001110 -
b00000000000101011000010110010011 C
b00000000000000000000000000000001 D
b00000000000000000000000000001111 E
b00001 M
b01011 N
b00000000000000000000000000000001 P
b00000000000000000000000000000001 Q
1R
b00000000000000000000000000001110 T
b00000000000000000000000000010000 U
b00000000000000000000000000010001 V
b00000000000000000000000000010100 W
b00000000000000000000000000010100 X
#190
0R
#192
b00000000000000000000000000001111 .
b11111110011001011001110011100011 C
b11111111111111111111111111111000 D
b11111111111111111111111100010000 E
0F
0G
1H
b001 J
b1100011 K
b00110 M
b11001 N
b00000000000000000000000000001111 O
b00000000000000000000000011111111 P
b11111111111111111111111111111000 Q
1R
b00000000000000000000000000010100 U
b00000000000000000000000000001100 V
b00000000000000000000000000001100 W
b00000000000000000000000000011000 X
b00000000000000000000000011111111 Y
#194
0R
#196
b00000000000001011000010100010011 C
b00000000000000000000000000000000 D
b00000000000000000000000000001111 E
1F
1G
0H
b000 J
b0010011 K
b00000 M
b01010 N
b00000000000000000000000000000000 P
b00000000000000000000000000000000 Q
1R
b00000000000000000000000000001100 U
b00000000000000000000000000010000 W
b00000000000000000000000000010000 X
b00000000000000000000000000000000 Y
#198
0R
